upd_logger/__init__.py
upd_logger/upd_logger.py
upd_logger-1.0.0.dist-info/METADATA
upd_logger-1.0.0.dist-info/WHEEL
upd_logger-1.0.0.dist-info/top_level.txt
upd_logger-1.0.0.dist-info/RECORD
