Metadata-Version: 2.1
Name: upd-logger
Version: 1.0.0
Summary: A feature-rich logging solution with file rotation, size-based cleanup, and configurable formatting.
Home-page: https://github.com/droid-darkangel/upd_logger
Author: Darkangel
Author-email: llopnin@gmail.com
Classifier: Programming Language :: Python :: 3
Classifier: License :: OSI Approved :: MIT License
Classifier: Operating System :: OS Independent
Requires-Python: >=3.11
